{
  "project_info": {
    "project_number": "576149380294",
    "project_id": "ecommerce-app-97305",
    "storage_bucket": "ecommerce-app-97305.appspot.com"
  },
  "client": [
    {
      "client_info": {
        "mobilesdk_app_id": "1:576149380294:android:254d49ee33483aeba6cbc7",
        "android_client_info": {
          "package_name": "com.example.ecommerceapp"
        }
      },
      "oauth_client": [],
      "api_key": [
        {
          "current_key": "AIzaSyAEVZIAtnJu5nwOsmqnIcIRYKFdTsGMQ0s"
        }
      ],
      "services": {
        "appinvite_service": {
          "other_platform_oauth_client": []
        }
      }
    }
  ],
  "configuration_version": "1"
}